celestsp/__init__.py
celestsp/main.py
celestsp-0.2.37.dist-info/METADATA
celestsp-0.2.37.dist-info/WHEEL
celestsp-0.2.37.dist-info/entry_points.txt
celestsp-0.2.37.dist-info/licenses/LICENSE
celestsp-0.2.37.dist-info/RECORD
