Metadata-Version: 2.4
Name: celestsp
Version: 0.2.37
Summary: Celestial TSP is a Python script that calculates the optimal order of celestial bodies for observation based on their coordinates.
Project-URL: Homepage, https://github.com/rioriost/homebrew-celestsp
Project-URL: Issues, https://github.com/rioriost/homebrew-celestsp/issues
Author-email: Rio Fujita <rifujita@microsoft.com>
License: MIT License
License-File: LICENSE
Requires-Python: >=3.13
Requires-Dist: astropy>=7.2.0
Requires-Dist: matplotlib>=3.10.8
Requires-Dist: networkx>=3.6.1
Requires-Dist: pandas>=2.3.3
Requires-Dist: requests>=2.32.5
Requires-Dist: scipy>=1.16.3
